MANIFEST.in
manage.py
setup.cfg
setup.py
docs/conf.py
dynamicForms/JSONSerializers.py
dynamicForms/__init__.py
dynamicForms/admin.py
dynamicForms/auth.py
dynamicForms/cms_plugins.py
dynamicForms/fields.py
dynamicForms/middlets.py
dynamicForms/models.py
dynamicForms/my.conf.js
dynamicForms/serializers.py
dynamicForms/signals.py
dynamicForms/urls.py
dynamicForms/views.py
dynamicForms/fieldtypes/CIField.py
dynamicForms/fieldtypes/CheckboxField.py
dynamicForms/fieldtypes/EmailField.py
dynamicForms/fieldtypes/Field.py
dynamicForms/fieldtypes/FieldFactory.py
dynamicForms/fieldtypes/FileField.py
dynamicForms/fieldtypes/GeoField.py
dynamicForms/fieldtypes/ListField.py
dynamicForms/fieldtypes/ModelField.py
dynamicForms/fieldtypes/NumberField.py
dynamicForms/fieldtypes/SelectField.py
dynamicForms/fieldtypes/TextAreaField.py
dynamicForms/fieldtypes/TextField.py
dynamicForms/fieldtypes/__init__.py
dynamicForms/fieldtypes/field_type.py
dynamicForms/static/__init__.py
dynamicForms/static/angular/FileSaver.js
dynamicForms/static/angular/__init__.py
dynamicForms/static/angular/angular-charts.js
dynamicForms/static/angular/angular-charts.min.js
dynamicForms/static/angular/angular-file-upload-shim.js
dynamicForms/static/angular/angular-file-upload.js
dynamicForms/static/angular/angular-load.min.js
dynamicForms/static/angular/angular-mocks.js
dynamicForms/static/angular/angular-route.min.js
dynamicForms/static/angular/angular-sanitize.js
dynamicForms/static/angular/angular.js
dynamicForms/static/angular/angular.min.js
dynamicForms/static/angular/angular.min.js.map
dynamicForms/static/angular/bluebird.js
dynamicForms/static/angular/captcha.js
dynamicForms/static/angular/checklist-model.js
dynamicForms/static/angular/d3.js
dynamicForms/static/angular/d3.min.js
dynamicForms/static/angular/jspdf.js
dynamicForms/static/angular/jspdf.plugin.table.js
dynamicForms/static/angular/lodash.min.js
dynamicForms/static/angular/ng-csv.js
dynamicForms/static/angular/sortable.js
dynamic_forms.egg-info/PKG-INFO
dynamic_forms.egg-info/SOURCES.txt
dynamic_forms.egg-info/dependency_links.txt
dynamic_forms.egg-info/entry_points.txt
dynamic_forms.egg-info/requires.txt
dynamic_forms.egg-info/top_level.txt
dynamic_forms.egg-info/zip-safe