Metadata-Version: 1.1
Name: dynamic-forms
Version: 0.9
Summary: Django App to create dynamic Surveys
Home-page: https://github.com/trea-uy/django-survey
Author: PythonWarriors
Author-email: info@trea.uy
License: GNU
Keywords: Django Survey Framework
Platform: UNKNOWN
Classifier: Programming Language :: Python
Classifier: Programming Language :: Python :: 3.4
Classifier: License :: OSI Approved :: GNU General Public License (GPL)
Classifier: Operating System :: OS Independent
Classifier: Development Status :: 4 - Beta
Classifier: Environment :: Web Environment
Classifier: Intended Audience :: Information Technology
Classifier: Topic :: Internet :: WWW/HTTP :: WSGI :: Application
